pycronorg/__init__.py
pycronorg/exceptions.py
pycronorg/schemas.py
pycronorg/async/__init__.py
pycronorg/sync/__init__.py
pycronorg/sync/base.py
pycronorg/sync/jobs.py
pycronorg-0.0.10.dist-info/LICENSE
pycronorg-0.0.10.dist-info/METADATA
pycronorg-0.0.10.dist-info/WHEEL
pycronorg-0.0.10.dist-info/top_level.txt
pycronorg-0.0.10.dist-info/RECORD
